Metadata-Version: 2.1
Name: GenderPrediction
Version: 3.0
Summary: Classify the name based on given name
Home-page: UNKNOWN
Author: Sounak-Mukherjee
Author-email: sounak@pratilipi.com
License: MIT
Platform: UNKNOWN
License-File: LICENCE.txt
